luoxc_utils/__init__.py
luoxc_utils/core.py
luoxc_utils-2022.1.1.dist-info/METADATA
luoxc_utils-2022.1.1.dist-info/WHEEL
luoxc_utils-2022.1.1.dist-info/top_level.txt
luoxc_utils-2022.1.1.dist-info/RECORD
