Metadata-Version: 2.1
Name: luoxc-utils
Version: 2022.1.1
Summary: python utils by luoxc
Home-page: https://github.com/
Author: Luoxc
Author-email: buptfhxy@163.com
License: APACHE
Keywords: utils
Platform: UNKNOWN
